analytics/mayhem/adobe.py
analytics_mayhem_adobe-0.0.10.dist-info/METADATA
analytics_mayhem_adobe-0.0.10.dist-info/WHEEL
analytics_mayhem_adobe-0.0.10.dist-info/top_level.txt
analytics_mayhem_adobe-0.0.10.dist-info/RECORD
